safe_gpu/__init__.py
safe_gpu/safe_gpu.py
safe_gpu-2.0.0.dist-info/LICENSE
safe_gpu-2.0.0.dist-info/METADATA
safe_gpu-2.0.0.dist-info/WHEEL
safe_gpu-2.0.0.dist-info/top_level.txt
safe_gpu-2.0.0.dist-info/RECORD
