Metadata-Version: 2.1
Name: safe-gpu
Version: 2.0.0
Summary: A process-safe acquisition of exclusive GPUs
Author-email: Karel Beneš <ibenes@fit.vutbr.cz>
License: MIT License
Project-URL: repository, https://github.com/BUTSpeechFIT/safe_gpu
Keywords: GPU,Resource allocation
Classifier: Programming Language :: Python :: 3
Classifier: License :: OSI Approved :: MIT License
Classifier: Operating System :: POSIX
Requires-Python: >=3.6
License-File: LICENSE
